{"v":4,"entries":{"tilt-react-next-tilt--docs":{"id":"tilt-react-next-tilt--docs","title":"Tilt (react-next-tilt)","name":"Docs","importPath":"./src/stories/Tilt.stories.tsx","type":"docs","tags":["autodocs","docs"],"storiesImports":[]},"tilt-react-next-tilt--default":{"type":"story","id":"tilt-react-next-tilt--default","name":"Default","title":"Tilt (react-next-tilt)","importPath":"./src/stories/Tilt.stories.tsx","tags":["autodocs","story"]},"tilt-react-next-tilt--border-radius":{"type":"story","id":"tilt-react-next-tilt--border-radius","name":"Border Radius","title":"Tilt (react-next-tilt)","importPath":"./src/stories/Tilt.stories.tsx","tags":["autodocs","story"]},"tilt-react-next-tilt--scale":{"type":"story","id":"tilt-react-next-tilt--scale","name":"Scale","title":"Tilt (react-next-tilt)","importPath":"./src/stories/Tilt.stories.tsx","tags":["autodocs","story"]},"tilt-react-next-tilt--shadow":{"type":"story","id":"tilt-react-next-tilt--shadow","name":"Shadow","title":"Tilt (react-next-tilt)","importPath":"./src/stories/Tilt.stories.tsx","tags":["autodocs","story"]},"tilt-react-next-tilt--tilt-reset":{"type":"story","id":"tilt-react-next-tilt--tilt-reset","name":"Tilt Reset","title":"Tilt (react-next-tilt)","importPath":"./src/stories/Tilt.stories.tsx","tags":["autodocs","story"]},"tilt-react-next-tilt--tilt-reverse":{"type":"story","id":"tilt-react-next-tilt--tilt-reverse","name":"Tilt Reverse","title":"Tilt (react-next-tilt)","importPath":"./src/stories/Tilt.stories.tsx","tags":["autodocs","story"]},"tilt-react-next-tilt--tilt-max-angle":{"type":"story","id":"tilt-react-next-tilt--tilt-max-angle","name":"Tilt Max Angle","title":"Tilt (react-next-tilt)","importPath":"./src/stories/Tilt.stories.tsx","tags":["autodocs","story"]},"tilt-react-next-tilt--initial-angle":{"type":"story","id":"tilt-react-next-tilt--initial-angle","name":"Initial Angle","title":"Tilt (react-next-tilt)","importPath":"./src/stories/Tilt.stories.tsx","tags":["autodocs","story"]},"tilt-react-next-tilt--line-glare":{"type":"story","id":"tilt-react-next-tilt--line-glare","name":"Line Glare","title":"Tilt (react-next-tilt)","importPath":"./src/stories/Tilt.stories.tsx","tags":["autodocs","story"]},"tilt-react-next-tilt--spot-glare":{"type":"story","id":"tilt-react-next-tilt--spot-glare","name":"Spot Glare","title":"Tilt (react-next-tilt)","importPath":"./src/stories/Tilt.stories.tsx","tags":["autodocs","story"]},"tilt-react-next-tilt--perspective":{"type":"story","id":"tilt-react-next-tilt--perspective","name":"Perspective","title":"Tilt (react-next-tilt)","importPath":"./src/stories/Tilt.stories.tsx","tags":["autodocs","story"]},"tilt-react-next-tilt--disabled":{"type":"story","id":"tilt-react-next-tilt--disabled","name":"Disabled","title":"Tilt (react-next-tilt)","importPath":"./src/stories/Tilt.stories.tsx","tags":["autodocs","story"]},"tilt-react-next-tilt--full-page-listening":{"type":"story","id":"tilt-react-next-tilt--full-page-listening","name":"Full Page Listening","title":"Tilt (react-next-tilt)","importPath":"./src/stories/Tilt.stories.tsx","tags":["autodocs","story"]},"tilt-react-next-tilt--gyroscope":{"type":"story","id":"tilt-react-next-tilt--gyroscope","name":"Gyroscope","title":"Tilt (react-next-tilt)","importPath":"./src/stories/Tilt.stories.tsx","tags":["autodocs","story"]},"tilt-react-next-tilt--gyro-reverse":{"type":"story","id":"tilt-react-next-tilt--gyro-reverse","name":"Gyro Reverse","title":"Tilt (react-next-tilt)","importPath":"./src/stories/Tilt.stories.tsx","tags":["autodocs","story"]},"tilt-react-next-tilt--gyro-max-angle":{"type":"story","id":"tilt-react-next-tilt--gyro-max-angle","name":"Gyro Max Angle","title":"Tilt (react-next-tilt)","importPath":"./src/stories/Tilt.stories.tsx","tags":["autodocs","story"]}}}
